octodiary/__init__.py
octodiary/exceptions.py
octodiary/urls.py
octodiary/apis/__init__.py
octodiary/apis/async_.py
octodiary/apis/base.py
octodiary/apis/sync.py
octodiary/types/__init__.py
octodiary/types/captcha.py
octodiary/types/enter_sms_code.py
octodiary/types/model.py
octodiary/types/mobile/__init__.py
octodiary/types/mobile/class_members.py
octodiary/types/mobile/day_balance_info.py
octodiary/types/mobile/events.py
octodiary/types/mobile/family_profile.py
octodiary/types/mobile/family_status.py
octodiary/types/mobile/lesson_schedule_item.py
octodiary/types/mobile/marks.py
octodiary/types/mobile/meals_clients.py
octodiary/types/mobile/notification.py
octodiary/types/mobile/parallel_curriculum.py
octodiary/types/mobile/periods_schedules.py
octodiary/types/mobile/person_data.py
octodiary/types/mobile/rating.py
octodiary/types/mobile/school_info.py
octodiary/types/mobile/short_homeworks.py
octodiary/types/mobile/short_subject_marks.py
octodiary/types/mobile/subject_marks.py
octodiary/types/mobile/subject_marks_for_subject.py
octodiary/types/mobile/subjects.py
octodiary/types/mobile/user_childrens.py
octodiary/types/mobile/user_settings.py
octodiary/types/mobile/users_profiles_info.py
octodiary/types/mobile/visits.py
octodiary/types/web/__init__.py
octodiary/types/web/academic_year.py
octodiary/types/web/custom_event.py
octodiary/types/web/events.py
octodiary/types/web/person_data.py
octodiary/types/web/role.py
octodiary/types/web/session_user_info.py
octodiary/types/web/student_profile.py
octodiary/types/web/user.py
octodiary/types/web/user_children.py
octodiary/types/web/user_contact.py
octodiary/types/web/user_info.py
octodiary/types/web/web_family_profile.py
octodiary/types/web/web_organizations.py
octodiary-0.3.0.dist-info/METADATA
octodiary-0.3.0.dist-info/WHEEL
octodiary-0.3.0.dist-info/licenses/LICENSE
octodiary-0.3.0.dist-info/RECORD
