Metadata-Version: 2.1
Name: octodiary
Version: 0.3.0
Summary: Python библиотека для использования API: МЭШ / Моя Школа.
Project-URL: Bug Reports, https://github.com/OctoDiary/OctoDiary-py/issues
Project-URL: Examples, https://github.com/OctoDiary/OctoDiary-py/blob/main/Examples.md
Project-URL: Homepage, https://github.com/OctoDiary/OctoDiary-py
Project-URL: Organization, https://github.com/OctoDiary
Project-URL: Source, https://github.com/OctoDiary/OctoDiary-py
Project-URL: Telegram-Channel, https://t.me/OctoDiary
Author-email: Den4ikSuperOstryyPer4ik <oleynik.denis.2009@gmail.com>, bxkr <me@bxkr.org>
License-Expression: MIT
License-File: LICENSE
Keywords: api,myschool,myschool apimesh,octodiary,моя школа,мэш
Classifier: License :: OSI Approved :: MIT License
Classifier: Programming Language :: Python :: 3
Classifier: Programming Language :: Python :: 3 :: Only
Classifier: Programming Language :: Python :: 3.9
Classifier: Programming Language :: Python :: 3.10
Classifier: Programming Language :: Python :: 3.11
Requires-Python: >=3.9
Requires-Dist: aiohttp
Requires-Dist: fake-useragent
Requires-Dist: pydantic
